yak_server/__init__.py
yak_server/alembic.ini
yak_server/app.py
yak_server/health_check.py
yak_server/cli/__init__.py
yak_server/cli/admin.py
yak_server/cli/database.py
yak_server/cli/env.py
yak_server/cli/migration.py
yak_server/cli/score_board.py
yak_server/cli/sync.py
yak_server/data/euro_2016/common.json
yak_server/data/euro_2016/groups.json
yak_server/data/euro_2016/matches.json
yak_server/data/euro_2016/phases.json
yak_server/data/euro_2016/teams.json
yak_server/data/euro_2020/common.json
yak_server/data/euro_2020/groups.json
yak_server/data/euro_2020/matches.json
yak_server/data/euro_2020/phases.json
yak_server/data/euro_2020/teams.json
yak_server/data/euro_2024/common.json
yak_server/data/euro_2024/groups.json
yak_server/data/euro_2024/matches.json
yak_server/data/euro_2024/phases.json
yak_server/data/euro_2024/teams.json
yak_server/data/world_cup_2018/common.json
yak_server/data/world_cup_2018/groups.json
yak_server/data/world_cup_2018/matches.json
yak_server/data/world_cup_2018/phases.json
yak_server/data/world_cup_2018/teams.json
yak_server/data/world_cup_2022/common.json
yak_server/data/world_cup_2022/groups.json
yak_server/data/world_cup_2022/matches.json
yak_server/data/world_cup_2022/phases.json
yak_server/data/world_cup_2022/teams.json
yak_server/data/world_cup_2022/rules/492345de-8d4a-45b6-8b94-d219f2b0c3e9.json
yak_server/data/world_cup_2022/rules/62d46542-8cf1-4a3b-af77-a5086f10ac59.json
yak_server/data/world_cup_2026/common.json
yak_server/data/world_cup_2026/groups.json
yak_server/data/world_cup_2026/matches.json
yak_server/data/world_cup_2026/phases.json
yak_server/data/world_cup_2026/teams.json
yak_server/data/world_cup_2026/rules/62d46542-8cf1-4a3b-af77-a5086f10ac59.json
yak_server/database/__init__.py
yak_server/database/models.py
yak_server/database/query.py
yak_server/database/session.py
yak_server/database/settings.py
yak_server/database/migrations/README
yak_server/database/migrations/__init__.py
yak_server/database/migrations/env.py
yak_server-0.62.0.dist-info/METADATA
yak_server-0.62.0.dist-info/WHEEL
yak_server-0.62.0.dist-info/entry_points.txt
yak_server-0.62.0.dist-info/licenses/LICENSE
yak_server-0.62.0.dist-info/RECORD
