Metadata-Version: 2.4
Name: yak-server
Version: 0.62.0
Summary: Football bet rest server
Project-URL: Homepage, https://github.com/yak-toto/yak-server
Project-URL: Repository, https://github.com/yak-toto/yak-server
Author-email: Guillaume Le Pape <gui.lepape25@gmail.com>
License-Expression: MIT
License-File: LICENSE
Keywords: api,postgresql,rest
Classifier: Environment :: Web Environment
Classifier: Framework :: FastAPI
Classifier: Framework :: Pydantic
Classifier: Framework :: Pydantic :: 2
Classifier: License :: OSI Approved :: MIT License
Classifier: Operating System :: Unix
Classifier: Programming Language :: Python
Classifier: Programming Language :: Python :: 3
Classifier: Programming Language :: Python :: 3 :: Only
Classifier: Programming Language :: Python :: 3.10
Classifier: Programming Language :: Python :: 3.11
Classifier: Programming Language :: Python :: 3.12
Classifier: Programming Language :: Python :: 3.13
Classifier: Programming Language :: Python :: 3.14
Classifier: Topic :: Database
Classifier: Topic :: Database :: Database Engines/Servers
Classifier: Topic :: Internet :: WWW/HTTP
Classifier: Topic :: Internet :: WWW/HTTP :: HTTP Servers
Requires-Python: >=3.10
Requires-Dist: argon2-cffi==25.1.0
Requires-Dist: click==8.3.1
Requires-Dist: fastapi==0.128.0
Requires-Dist: psycopg[binary]==3.3.2
Requires-Dist: pydantic-settings==2.12.0
Requires-Dist: pyjwt==2.10.1
Requires-Dist: sqlalchemy==2.0.46
Provides-Extra: db-migration
Requires-Dist: alembic==1.18.1; extra == 'db-migration'
Provides-Extra: server
Requires-Dist: uvicorn==0.40.0; extra == 'server'
Provides-Extra: sync
Requires-Dist: beautifulsoup4[lxml]==4.14.3; extra == 'sync'
Requires-Dist: httpx==0.28.1; extra == 'sync'
